{
    "model": [
        {
            "name": "C",
            "value": -4.802551523239009,
            "longName": "conscientiousness"
        },
        {
            "name": "N",
            "value": 1.7293758495429739,
            "longName": "neuroticism"
        },
        {
            "name": "O",
            "value": -1.6817627471226526,
            "longName": "openess"
        },
        {
            "name": "E",
            "value": -1.431077315275724,
            "longName": "extraversion"
        },
        {
            "name": "A",
            "value": 0.518381830713885,
            "longName": "agreeablility"
        }
    ],
    "meta": {
        "product": "Top Class Education",
        "gender": "female"
    },
    "image": "1531905679437.png"
}